[{"id": "ts_shadow_wilds", "name": "Shadow Wilds", "provider": "thunderspin", "rtp": "96.0", "vol_range": "high", "genre": "slot", "provider_name": "ThunderSpin"}, {"id": "ts_jingle_blast", "name": "Jingle Blast", "provider": "thunderspin", "rtp": "96.02", "vol_range": "high", "genre": "slot", "provider_name": "ThunderSpin"}, {"id": "ts_fiery_fortune", "name": "Fiery Fortune", "provider": "thunderspin", "rtp": "96.0", "vol_range": "high", "genre": "slot", "provider_name": "ThunderSpin"}, {"id": "ts_loco_luck", "name": "Loco Luck", "provider": "thunderspin", "rtp": "96.0", "vol_range": "high", "genre": "slot", "provider_name": "ThunderSpin"}, {"id": "ts_candy_blast", "name": "Candy Blast", "provider": "thunderspin", "rtp": "96.0", "vol_range": "high", "genre": "slot", "provider_name": "ThunderSpin"}, {"id": "ts_savannah_spins", "name": "Savannah Spins", "provider": "thunderspin", "rtp": "96.0", "vol_range": "high", "genre": "slot", "provider_name": "ThunderSpin"}, {"id": "ts_thunder_fruits", "name": "Thunder Fruits", "provider": "thunderspin", "rtp": "96.0", "vol_range": "high", "genre": "slot", "provider_name": "ThunderSpin"}, {"id": "ts_steam_wilds", "name": "Steam Wilds", "provider": "thunderspin", "rtp": "96.03", "vol_range": "high", "genre": "slot", "provider_name": "ThunderSpin"}, {"id": "ts_tundra_treasures", "name": "Tundra Treasures", "provider": "thunderspin", "rtp": "96.0", "vol_range": "high", "genre": "slot", "provider_name": "ThunderSpin"}, {"id": "ts_holmes_vs_moriarty", "name": "Holmes vs Moriarty", "provider": "thunderspin", "rtp": "96.0", "vol_range": "high", "genre": "slot", "provider_name": "ThunderSpin"}, {"id": "ts_santa_vs_krampus", "name": "Santa vs Krampus", "provider": "thunderspin", "rtp": "96.0", "vol_range": "high", "genre": "slot", "provider_name": "ThunderSpin"}, {"id": "ts_aztec_artefacts_10000", "name": "Aztec Artefacts 10000", "provider": "thunderspin", "rtp": "95.6", "vol_range": "high", "genre": "slot", "provider_name": "ThunderSpin"}, {"id": "ts_book_of_witches", "name": "Book of Witches", "provider": "thunderspin", "rtp": "95.8", "vol_range": "high", "genre": "slot", "provider_name": "ThunderSpin"}, {"id": "ts_pyramids_deluxe", "name": "Pyramids Deluxe", "provider": "thunderspin", "rtp": "96.0", "vol_range": "high", "genre": "slot", "provider_name": "ThunderSpin"}, {"id": "ts_rich_leprechaun_megaways", "name": "Rich Leprechaun Megaways", "provider": "thunderspin", "rtp": "96.1", "vol_range": "high", "genre": "slot", "provider_name": "ThunderSpin"}, {"id": "ts_money_ways", "name": "Money Ways", "provider": "thunderspin", "rtp": "96.04", "vol_range": "high", "genre": "slot", "provider_name": "ThunderSpin"}, {"id": "ts_book_of_games_20", "name": "Book of Games 20", "provider": "thunderspin", "rtp": "95.58", "vol_range": "high", "genre": "slot", "provider_name": "ThunderSpin"}, {"id": "ts_book_of_egypt", "name": "Book of Egypt", "provider": "thunderspin", "rtp": "95.77", "vol_range": "high", "genre": "slot", "provider_name": "ThunderSpin"}, {"id": "ts_aztec_artefacts", "name": "Aztec Artefacts", "provider": "thunderspin", "rtp": "95.61", "vol_range": "high", "genre": "slot", "provider_name": "ThunderSpin"}, {"id": "ts_sakura_mystery", "name": "Sakura Mystery", "provider": "thunderspin", "rtp": "95.6", "vol_range": "high", "genre": "slot", "provider_name": "ThunderSpin"}, {"id": "ts_western_riches", "name": "Western Riches", "provider": "thunderspin", "rtp": "96.1", "vol_range": "middle", "genre": "slot", "provider_name": "ThunderSpin"}, {"id": "ts_book_of_games", "name": "Book of Games", "provider": "thunderspin", "rtp": "95.7", "vol_range": "high", "genre": "slot", "provider_name": "ThunderSpin"}, {"id": "ts_pyramids", "name": "Pyramids", "provider": "thunderspin", "rtp": "95.8", "vol_range": "high", "genre": "slot", "provider_name": "ThunderSpin"}, {"id": "ts_book_of_jam", "name": "Book of Jam", "provider": "thunderspin", "rtp": "95.9", "vol_range": "high", "genre": "slot", "provider_name": "ThunderSpin"}, {"id": "ts_sky_lanterns", "name": "Sky Lanterns", "provider": "thunderspin", "rtp": "95.8", "vol_range": "middle", "genre": "slot", "provider_name": "ThunderSpin"}, {"id": "ts_halloween_witch_party", "name": "Halloween Witch Party", "provider": "thunderspin", "rtp": "95.6", "vol_range": "middle", "genre": "slot", "provider_name": "ThunderSpin"}, {"id": "ts_kingdom_of_glory", "name": "Kingdom of Glory", "provider": "thunderspin", "rtp": "96.2", "vol_range": "high", "genre": "slot", "provider_name": "ThunderSpin"}, {"id": "ts_book_of_treasures", "name": "Book of Treasures", "provider": "thunderspin", "rtp": "92.19", "vol_range": "high", "genre": "slot", "provider_name": "ThunderSpin"}, {"id": "ts_vikings_frozen_gods", "name": "Vikings: Frozen Gods", "provider": "thunderspin", "rtp": "96.3", "vol_range": "high", "genre": "slot", "provider_name": "ThunderSpin"}, {"id": "ts_angels_vs_demons", "name": "Angels vs Demons", "provider": "thunderspin", "rtp": "96.0", "vol_range": "high", "genre": "slot", "provider_name": "ThunderSpin"}, {"id": "ts_spy_girls", "name": "Spy Girls", "provider": "thunderspin", "rtp": "95.4", "vol_range": "middle", "genre": "slot", "provider_name": "ThunderSpin"}, {"id": "ts_egypt_story", "name": "Egypt Story", "provider": "thunderspin", "rtp": "96.3", "vol_range": "high", "genre": "slot", "provider_name": "ThunderSpin"}, {"id": "ts_stellar", "name": "Stellar", "provider": "thunderspin", "rtp": "96.0", "vol_range": "middle", "genre": "slot", "provider_name": "ThunderSpin"}, {"id": "ts_cute_farm", "name": "Cute Farm", "provider": "thunderspin", "rtp": "95.7", "vol_range": "high", "genre": "slot", "provider_name": "ThunderSpin"}, {"id": "ts_world_cup_football", "name": "World Cup Football", "provider": "thunderspin", "rtp": "95.4", "vol_range": "middle", "genre": "slot", "provider_name": "ThunderSpin"}, {"id": "ts_the_money", "name": "The Money", "provider": "thunderspin", "rtp": "96.2", "vol_range": "middle", "genre": "slot", "provider_name": "ThunderSpin"}, {"id": "ts_zombie_slot_deluxe", "name": "Zombie Slot Deluxe", "provider": "thunderspin", "rtp": "96.1", "vol_range": "middle", "genre": "slot", "provider_name": "ThunderSpin"}, {"id": "ts_space_jail", "name": "Space Jail", "provider": "thunderspin", "rtp": "95.5", "vol_range": "high", "genre": "slot", "provider_name": "ThunderSpin"}, {"id": "ts_snailtown", "name": "Snailtown", "provider": "thunderspin", "rtp": "95.7", "vol_range": "low", "genre": "slot", "provider_name": "ThunderSpin"}, {"id": "ts_the_queen_of_spades", "name": "The Queen of Spades", "provider": "thunderspin", "rtp": "96.0", "vol_range": "low", "genre": "slot", "provider_name": "ThunderSpin"}, {"id": "ts_necronomicon", "name": "Necronomicon", "provider": "thunderspin", "rtp": "95.3", "vol_range": "high", "genre": "slot", "provider_name": "ThunderSpin"}, {"id": "ts_monster_sushi", "name": "Monster Sushi", "provider": "thunderspin", "rtp": "95.6", "vol_range": "middle", "genre": "slot", "provider_name": "ThunderSpin"}, {"id": "ts_magic_jam", "name": "Magic Jam", "provider": "thunderspin", "rtp": "94.6", "vol_range": "middle", "genre": "slot", "provider_name": "ThunderSpin"}, {"id": "ts_jolly_roger", "name": "Jolly Roger", "provider": "thunderspin", "rtp": "94.2", "vol_range": "low", "genre": "slot", "provider_name": "ThunderSpin"}, {"id": "ts_joker_jack", "name": "Joker Jack", "provider": "thunderspin", "rtp": "95.5", "vol_range": "low", "genre": "slot", "provider_name": "ThunderSpin"}, {"id": "ts_indian_gold", "name": "Indian Gold", "provider": "thunderspin", "rtp": "95.5", "vol_range": "middle", "genre": "slot", "provider_name": "ThunderSpin"}, {"id": "ts_gold_sea", "name": "Gold Sea", "provider": "thunderspin", "rtp": "95.8", "vol_range": "low", "genre": "slot", "provider_name": "ThunderSpin"}, {"id": "ts_crazy_new_year", "name": "Crazy New Year", "provider": "thunderspin", "rtp": "95.1", "vol_range": "low", "genre": "slot", "provider_name": "ThunderSpin"}, {"id": "ts_circus_train", "name": "Circus Train", "provider": "thunderspin", "rtp": "94.3", "vol_range": "low", "genre": "slot", "provider_name": "ThunderSpin"}, {"id": "ts_chibi_slot", "name": "Chibi Slot", "provider": "thunderspin", "rtp": "95.7", "vol_range": "low", "genre": "slot", "provider_name": "ThunderSpin"}, {"id": "ts_candyland", "name": "Candyland", "provider": "thunderspin", "rtp": "95.0", "vol_range": "high", "genre": "slot", "provider_name": "ThunderSpin"}, {"id": "ts_calipso", "name": "Calipso", "provider": "thunderspin", "rtp": "95.8", "vol_range": "low", "genre": "slot", "provider_name": "ThunderSpin"}, {"id": "ts_atomic_mushrooms", "name": "Atomic Mushrooms", "provider": "thunderspin", "rtp": "95.5", "vol_range": "low", "genre": "slot", "provider_name": "ThunderSpin"}, {"id": "ts_animals_steam", "name": "Animals Steam", "provider": "thunderspin", "rtp": "95.4", "vol_range": "middle", "genre": "slot", "provider_name": "ThunderSpin"}]